fec_filing_iterator/__init__.py
fec_filing_iterator/_version.py
fec_filing_iterator/errors.py
fec_filing_iterator/factories.py
fec_filing_iterator/filing_iterator.py
fec_filing_iterator-1.0.0.dist-info/LICENSE
fec_filing_iterator-1.0.0.dist-info/METADATA
fec_filing_iterator-1.0.0.dist-info/WHEEL
fec_filing_iterator-1.0.0.dist-info/top_level.txt
fec_filing_iterator-1.0.0.dist-info/RECORD
