Metadata-Version: 2.1
Name: fec-filing-iterator
Version: 1.0.0
Summary: Utility to iterate over FEC filings through the FEC API
Home-page: https://github.com/andrewmilligan/fec-filing-iterator
Author: Ander Milligan
Author-email: andrew.i.milligan@gmail.com
License: ISC
Keywords: fec campaign finance elections
Platform: UNKNOWN
Requires-Dist: requests (>=2.19.0)
